{
  "name": "Homayoun Tabandeh",
  "credentials": "M.D.",
  "specialty": "Ophthalmology",
  "city": "Los Angeles",
  "state": "CA",
  "entity_type": "Individual",
  "yearly_payments": [
    {
      "year": 2014,
      "total_payments": 1500641.19,
      "total_services": 14105,
      "total_beneficiaries": 21,
      "avg_submitted": 348.11,
      "avg_paid": 106.39
    },
    {
      "year": 2015,
      "total_payments": 1558696.59,
      "total_services": 14155,
      "total_beneficiaries": 20,
      "avg_submitted": 369.83,
      "avg_paid": 110.12
    },
    {
      "year": 2016,
      "total_payments": 1680722.2,
      "total_services": 14713,
      "total_beneficiaries": 20,
      "avg_submitted": 404.03,
      "avg_paid": 114.23
    },
    {
      "year": 2017,
      "total_payments": 2291907.33,
      "total_services": 16613,
      "total_beneficiaries": 20,
      "avg_submitted": 481.6,
      "avg_paid": 137.96
    },
    {
      "year": 2018,
      "total_payments": 2590157.42,
      "total_services": 19161,
      "total_beneficiaries": 21,
      "avg_submitted": 467.57,
      "avg_paid": 135.18
    },
    {
      "year": 2019,
      "total_payments": 3037527.53,
      "total_services": 19114,
      "total_beneficiaries": 19,
      "avg_submitted": 558.66,
      "avg_paid": 158.92
    },
    {
      "year": 2020,
      "total_payments": 3551119.26,
      "total_services": 18462,
      "total_beneficiaries": 19,
      "avg_submitted": 704.68,
      "avg_paid": 192.35
    },
    {
      "year": 2021,
      "total_payments": 3939378.65,
      "total_services": 18226,
      "total_beneficiaries": 19,
      "avg_submitted": 788.58,
      "avg_paid": 216.14
    },
    {
      "year": 2022,
      "total_payments": 4707180.32,
      "total_services": 21843,
      "total_beneficiaries": 19,
      "avg_submitted": 796.91,
      "avg_paid": 215.5
    },
    {
      "year": 2023,
      "total_payments": 5147902.07,
      "total_services": 38232,
      "total_beneficiaries": 19,
      "avg_submitted": 487.17,
      "avg_paid": 134.65
    }
  ],
  "overall": {
    "total_payments": 30005232.56,
    "total_services": 194624,
    "total_beneficiaries": 197,
    "avg_markup_ratio": 3.57,
    "years_active": 10
  },
  "top_procedures": [
    {
      "code": "J0178",
      "description": "Injection, aflibercept, 1 mg",
      "services": 20427,
      "payments": 14986289.02,
      "avg_markup": 3.29
    },
    {
      "code": "J2778",
      "description": "Injection, ranibizumab, 0.1 mg",
      "services": 10759,
      "payments": 2989082.21,
      "avg_markup": 3.39
    },
    {
      "code": "67028",
      "description": "Injection of drug into eye",
      "services": 24547,
      "payments": 2343294.2,
      "avg_markup": 7.39
    },
    {
      "code": "92014",
      "description": "Established patient complete exam of visual system",
      "services": 19982,
      "payments": 1953232.41,
      "avg_markup": 2.57
    },
    {
      "code": "Q5128",
      "description": "Injection, ranibizumab-eqrn (cimerli), biosimilar, 0.1 mg",
      "services": 7426,
      "payments": 1629153.07,
      "avg_markup": 3.18
    },
    {
      "code": "92134",
      "description": "Imaging of retina",
      "services": 44330,
      "payments": 1555894.73,
      "avg_markup": 4.14
    },
    {
      "code": "92012",
      "description": "Established patient problem focused exam of visual system",
      "services": 20365,
      "payments": 1481585.88,
      "avg_markup": 2.61
    },
    {
      "code": "J2777",
      "description": "Injection, faricimab-svoa, 0.1 mg",
      "services": 15720,
      "payments": 457173.16,
      "avg_markup": 2.91
    },
    {
      "code": "J7999",
      "description": "Compounded drug, not otherwise classified",
      "services": 6598,
      "payments": 400548.94,
      "avg_markup": 1.77
    },
    {
      "code": "92004",
      "description": "New patient complete exam of visual system",
      "services": 2887,
      "payments": 325285.87,
      "avg_markup": 2.48
    },
    {
      "code": "92235",
      "description": "Exam of retinal blood vessels using a special camera after injection of a dye",
      "services": 2840,
      "payments": 258979.0,
      "avg_markup": 2.93
    },
    {
      "code": "67228",
      "description": "Destruction of leaking blood vessels of retina using laser",
      "services": 541,
      "payments": 258231.38,
      "avg_markup": 3.96
    },
    {
      "code": "67042",
      "description": "Removal of membrane of retina with removal of internal limiting membrane of retina",
      "services": 207,
      "payments": 210545.54,
      "avg_markup": 5.95
    },
    {
      "code": "J9035",
      "description": "Injection, bevacizumab, 10 mg",
      "services": 3269,
      "payments": 180286.51,
      "avg_markup": 3.0
    },
    {
      "code": "J3490",
      "description": "Unclassified drugs",
      "services": 160,
      "payments": 161231.27,
      "avg_markup": 3.63
    },
    {
      "code": "99204",
      "description": "New patient office or other outpatient visit, 45-59 minutes",
      "services": 1016,
      "payments": 125157.22,
      "avg_markup": 2.32
    },
    {
      "code": "J3590",
      "description": "Unclassified biologics",
      "services": 1179,
      "payments": 111292.52,
      "avg_markup": 2.1
    },
    {
      "code": "92250",
      "description": "Photography of the retina",
      "services": 1736,
      "payments": 77966.95,
      "avg_markup": 2.47
    },
    {
      "code": "67210",
      "description": "Laser destruction of retinal growth, 1 or more sessions",
      "services": 140,
      "payments": 62516.98,
      "avg_markup": 3.81
    },
    {
      "code": "67145",
      "description": "Photocoagulation treatment to prevent detachment of retina",
      "services": 142,
      "payments": 54105.77,
      "avg_markup": 4.4
    }
  ]
}