{
  "name": "Matthew Nora",
  "credentials": "MD",
  "specialty": "Cardiology",
  "city": "Downers Grove",
  "state": "IL",
  "entity_type": "Individual",
  "yearly_payments": [
    {
      "year": 2014,
      "total_payments": 327942.94,
      "total_services": 4839,
      "total_beneficiaries": 3468,
      "avg_submitted": 482.3,
      "avg_paid": 118.31
    },
    {
      "year": 2015,
      "total_payments": 236731.34,
      "total_services": 3917,
      "total_beneficiaries": 2726,
      "avg_submitted": 395.34,
      "avg_paid": 93.77
    },
    {
      "year": 2016,
      "total_payments": 250071.33,
      "total_services": 4251,
      "total_beneficiaries": 2899,
      "avg_submitted": 408.88,
      "avg_paid": 94.6
    },
    {
      "year": 2017,
      "total_payments": 262982.37,
      "total_services": 4679,
      "total_beneficiaries": 3197,
      "avg_submitted": 327.41,
      "avg_paid": 74.89
    },
    {
      "year": 2018,
      "total_payments": 341876.94,
      "total_services": 6730,
      "total_beneficiaries": 4912,
      "avg_submitted": 349.7,
      "avg_paid": 82.37
    },
    {
      "year": 2019,
      "total_payments": 368567.48,
      "total_services": 7076,
      "total_beneficiaries": 5248,
      "avg_submitted": 266.9,
      "avg_paid": 59.42
    },
    {
      "year": 2020,
      "total_payments": 387064.64,
      "total_services": 6954,
      "total_beneficiaries": 4768,
      "avg_submitted": 352.32,
      "avg_paid": 83.26
    },
    {
      "year": 2021,
      "total_payments": 381101.64,
      "total_services": 6375,
      "total_beneficiaries": 4938,
      "avg_submitted": 299.38,
      "avg_paid": 73.75
    },
    {
      "year": 2022,
      "total_payments": 339767.92,
      "total_services": 6526,
      "total_beneficiaries": 5054,
      "avg_submitted": 236.98,
      "avg_paid": 57.5
    },
    {
      "year": 2023,
      "total_payments": 397804.46,
      "total_services": 8120,
      "total_beneficiaries": 5811,
      "avg_submitted": 218.09,
      "avg_paid": 52.05
    }
  ],
  "top_procedures": [
    {
      "code": "99214",
      "description": "Established patient office or other outpatient, visit typically 25 minutes",
      "services": 11137,
      "payments": 936262.69,
      "avg_markup": 2.68
    },
    {
      "code": "99232",
      "description": "Subsequent hospital inpatient care, typically 25 minutes per day",
      "services": 5227,
      "payments": 316688.91,
      "avg_markup": 2.49
    },
    {
      "code": "99233",
      "description": "Subsequent hospital inpatient care, typically 35 minutes per day",
      "services": 3320,
      "payments": 295654.97,
      "avg_markup": 2.45
    },
    {
      "code": "99223",
      "description": "Initial hospital inpatient care, typically 70 minutes per day",
      "services": 1210,
      "payments": 198852.96,
      "avg_markup": 2.59
    },
    {
      "code": "99215",
      "description": "Established patient office or other outpatient, visit typically 40 minutes",
      "services": 1220,
      "payments": 154815.35,
      "avg_markup": 2.39
    },
    {
      "code": "33208",
      "description": "Insertion of new or replacement of permanent pacemaker including upper and lower chamber electrodes",
      "services": 327,
      "payments": 150646.77,
      "avg_markup": 4.76
    },
    {
      "code": "99205",
      "description": "New patient office or other outpatient visit, typically 60 minutes",
      "services": 754,
      "payments": 128804.46,
      "avg_markup": 2.58
    },
    {
      "code": "93280",
      "description": "Evaluation, testing, and programming adjustment of permanent dual lead pacemaker system with physician analysis, review, and report",
      "services": 1675,
      "payments": 90109.31,
      "avg_markup": 3.15
    },
    {
      "code": "93296",
      "description": "Remote evaluations of defibrillator transmissions, technician review, support and distribution of results up to 90 days",
      "services": 4435,
      "payments": 84090.14,
      "avg_markup": 4.69
    },
    {
      "code": "G2066",
      "description": "Interrogation device evaluation(s), (remote) up to 30 days; implantable cardiovascular physiologic monitor system, implantable loop recorder system, or subcutaneous cardiac rhythm monitor system, remote data acquisition(s), receipt of transmissions and tec",
      "services": 601,
      "payments": 72339.95,
      "avg_markup": 3.12
    },
    {
      "code": "33249",
      "description": "Insertion or replacement of single or dual chamber pacing defibrillator leads",
      "services": 87,
      "payments": 69465.58,
      "avg_markup": 4.4
    },
    {
      "code": "93294",
      "description": "Remote evaluations of single, dual, or multiple lead pacemaker with physician analysis, review, and report up to 90 days",
      "services": 2881,
      "payments": 65558.25,
      "avg_markup": 4.27
    },
    {
      "code": "99204",
      "description": "New patient office or other outpatient visit, typically 45 minutes",
      "services": 513,
      "payments": 63986.93,
      "avg_markup": 2.87
    },
    {
      "code": "99222",
      "description": "Initial hospital inpatient care, typically 50 minutes per day",
      "services": 515,
      "payments": 58208.59,
      "avg_markup": 2.6
    },
    {
      "code": "93295",
      "description": "Remote evaluations of single, dual, or multiple lead cardioverter-defibrillator with physician analysis, review, and report up to 90 days",
      "services": 1787,
      "payments": 57635.31,
      "avg_markup": 5.97
    },
    {
      "code": "93299",
      "description": "Remote evaluations of implantable heart recorder system including transmissions, technician review, support, and distribution of results up to 30 days",
      "services": 358,
      "payments": 50769.18,
      "avg_markup": 2.69
    },
    {
      "code": "92960",
      "description": "External shock to heart to regulate heart beat",
      "services": 529,
      "payments": 48590.66,
      "avg_markup": 8.1
    },
    {
      "code": "93000",
      "description": "Routine EKG using at least 12 leads including interpretation and report",
      "services": 3794,
      "payments": 47202.43,
      "avg_markup": 5.81
    },
    {
      "code": "93283",
      "description": "Evaluation, testing, and programming adjustment of permanent dual lead cardioverter-defibrillator including physician analysis, review, and report",
      "services": 508,
      "payments": 34631.63,
      "avg_markup": 3.39
    },
    {
      "code": "33228",
      "description": "Removal and replacement of dual lead permanent pacemaker pulse generator",
      "services": 110,
      "payments": 33599.96,
      "avg_markup": 4.05
    }
  ],
  "overall": {
    "years_active": 10,
    "total_payments": 3293911.08,
    "total_services": 59467,
    "total_beneficiaries": 43021,
    "avg_markup_ratio": 3.29
  }
}