{
  "name": "Richard Thoms",
  "credentials": "M.D.",
  "specialty": "Orthopedic Surgery",
  "city": "Niantic",
  "state": "CT",
  "entity_type": "Individual",
  "yearly_payments": [
    {
      "year": 2014,
      "total_payments": 385898.86,
      "total_services": 3045,
      "total_beneficiaries": 2285,
      "avg_submitted": 820.02,
      "avg_paid": 281.13
    },
    {
      "year": 2015,
      "total_payments": 383324.89,
      "total_services": 3181,
      "total_beneficiaries": 2318,
      "avg_submitted": 691.88,
      "avg_paid": 250.26
    },
    {
      "year": 2016,
      "total_payments": 363014.24,
      "total_services": 2886,
      "total_beneficiaries": 2285,
      "avg_submitted": 572.32,
      "avg_paid": 144.84
    },
    {
      "year": 2017,
      "total_payments": 374775.1,
      "total_services": 2587,
      "total_beneficiaries": 1957,
      "avg_submitted": 1284.85,
      "avg_paid": 238.2
    },
    {
      "year": 2018,
      "total_payments": 345791.37,
      "total_services": 2522,
      "total_beneficiaries": 1850,
      "avg_submitted": 1036.24,
      "avg_paid": 250.07
    },
    {
      "year": 2019,
      "total_payments": 308828.06,
      "total_services": 1773,
      "total_beneficiaries": 1423,
      "avg_submitted": 820.75,
      "avg_paid": 218.07
    },
    {
      "year": 2020,
      "total_payments": 229172.18,
      "total_services": 1297,
      "total_beneficiaries": 1134,
      "avg_submitted": 868.02,
      "avg_paid": 225.09
    },
    {
      "year": 2021,
      "total_payments": 255504.49,
      "total_services": 1227,
      "total_beneficiaries": 1109,
      "avg_submitted": 1394.03,
      "avg_paid": 350.59
    },
    {
      "year": 2022,
      "total_payments": 213875.39,
      "total_services": 1210,
      "total_beneficiaries": 1079,
      "avg_submitted": 1209.09,
      "avg_paid": 298.35
    },
    {
      "year": 2023,
      "total_payments": 218543.56,
      "total_services": 1527,
      "total_beneficiaries": 1304,
      "avg_submitted": 745.6,
      "avg_paid": 190.63
    }
  ],
  "top_procedures": [
    {
      "code": "27447",
      "description": "Repair of knee joint",
      "services": 901,
      "payments": 1044003.71,
      "avg_markup": 4.23
    },
    {
      "code": "27130",
      "description": "Replacement of thigh bone and hip joint prosthesis",
      "services": 638,
      "payments": 736368.9,
      "avg_markup": 4.53
    },
    {
      "code": "99214",
      "description": "Established patient office or other outpatient, visit typically 25 minutes",
      "services": 1611,
      "payments": 137493.76,
      "avg_markup": 1.99
    },
    {
      "code": "99213",
      "description": "Established patient office or other outpatient visit, typically 15 minutes",
      "services": 2045,
      "payments": 117091.08,
      "avg_markup": 2.01
    },
    {
      "code": "20610",
      "description": "Aspiration and/or injection of large joint or joint capsule",
      "services": 2048,
      "payments": 107446.51,
      "avg_markup": 4.38
    },
    {
      "code": "99204",
      "description": "New patient office or other outpatient visit, typically 45 minutes",
      "services": 774,
      "payments": 94998.51,
      "avg_markup": 2.18
    },
    {
      "code": "99215",
      "description": "Established patient office or other outpatient, visit typically 40 minutes",
      "services": 788,
      "payments": 94914.66,
      "avg_markup": 1.99
    },
    {
      "code": "73564",
      "description": "X-ray of knee, 4 or more views",
      "services": 2839,
      "payments": 88687.35,
      "avg_markup": 4.14
    },
    {
      "code": "27236",
      "description": "Open treatment of broken thigh bone with insertion of hardware or prosthetic replacement",
      "services": 81,
      "payments": 83533.62,
      "avg_markup": 3.54
    },
    {
      "code": "J7324",
      "description": "Hyaluronan or derivative, orthovisc, for intra-articular injection, per dose",
      "services": 642,
      "payments": 80127.65,
      "avg_markup": 2.81
    },
    {
      "code": "J7323",
      "description": "Hyaluronan or derivative, euflexxa, for intra-articular injection, per dose",
      "services": 606,
      "payments": 70123.59,
      "avg_markup": 2.37
    },
    {
      "code": "27245",
      "description": "Surgical treatment of broken thigh bone",
      "services": 59,
      "payments": 60283.68,
      "avg_markup": 4.22
    },
    {
      "code": "73502",
      "description": "X-ray of hip with pelvis, 2-3 views",
      "services": 1834,
      "payments": 48320.56,
      "avg_markup": 3.52
    },
    {
      "code": "76942",
      "description": "Ultrasonic guidance imaging supervision and interpretation for insertion of needle",
      "services": 774,
      "payments": 42576.9,
      "avg_markup": 4.54
    },
    {
      "code": "27487",
      "description": "Revision of lower thigh bone and both shin bone components of total knee joint prosthesis",
      "services": 25,
      "payments": 38160.24,
      "avg_markup": 3.14
    },
    {
      "code": "23472",
      "description": "Prosthetic repair of shoulder joint",
      "services": 24,
      "payments": 30308.48,
      "avg_markup": 4.69
    },
    {
      "code": "20611",
      "description": "Aspiration and/or injection of major joint or joint capsule with recording and reporting using ultrasound guidance",
      "services": 328,
      "payments": 27714.08,
      "avg_markup": 5.42
    },
    {
      "code": "G0180",
      "description": "Physician certification for medicare-covered home health  services under a home health plan of care (patient not present), including contacts with home health agency and review of reports of patient status required by physicians to affirm the initial imple",
      "services": 543,
      "payments": 23963.94,
      "avg_markup": 1.83
    },
    {
      "code": "99223",
      "description": "Initial hospital inpatient care, typically 70 minutes per day",
      "services": 130,
      "payments": 21477.57,
      "avg_markup": 1.51
    },
    {
      "code": "99203",
      "description": "New patient office or other outpatient visit, typically 30 minutes",
      "services": 263,
      "payments": 21286.19,
      "avg_markup": 2.29
    }
  ],
  "overall": {
    "years_active": 10,
    "total_payments": 3078728.15,
    "total_services": 21255,
    "total_beneficiaries": 16744,
    "avg_markup_ratio": 3.79
  }
}