{
  "name": "Ricardo Abreu",
  "credentials": "MD",
  "specialty": "Pulmonary Disease",
  "city": "Weslaco",
  "state": "TX",
  "entity_type": "Individual",
  "yearly_payments": [
    {
      "year": 2014,
      "total_payments": 404439.85,
      "total_services": 4679,
      "total_beneficiaries": 3594,
      "avg_submitted": 253.23,
      "avg_paid": 76.85
    },
    {
      "year": 2015,
      "total_payments": 407047.24,
      "total_services": 5532,
      "total_beneficiaries": 4230,
      "avg_submitted": 246.97,
      "avg_paid": 73.35
    },
    {
      "year": 2016,
      "total_payments": 389067.99,
      "total_services": 5985,
      "total_beneficiaries": 4606,
      "avg_submitted": 213.47,
      "avg_paid": 66.76
    },
    {
      "year": 2017,
      "total_payments": 384701.47,
      "total_services": 5705,
      "total_beneficiaries": 4406,
      "avg_submitted": 223.34,
      "avg_paid": 71.13
    },
    {
      "year": 2018,
      "total_payments": 340528.32,
      "total_services": 4456,
      "total_beneficiaries": 3473,
      "avg_submitted": 226.12,
      "avg_paid": 72.66
    },
    {
      "year": 2019,
      "total_payments": 322622.55,
      "total_services": 4515,
      "total_beneficiaries": 3490,
      "avg_submitted": 233.06,
      "avg_paid": 73.01
    },
    {
      "year": 2020,
      "total_payments": 311788.48,
      "total_services": 3303,
      "total_beneficiaries": 2394,
      "avg_submitted": 266.32,
      "avg_paid": 89.6
    },
    {
      "year": 2021,
      "total_payments": 239376.31,
      "total_services": 2999,
      "total_beneficiaries": 2347,
      "avg_submitted": 196.67,
      "avg_paid": 84.02
    },
    {
      "year": 2022,
      "total_payments": 190428.4,
      "total_services": 2595,
      "total_beneficiaries": 2119,
      "avg_submitted": 213.54,
      "avg_paid": 85.12
    },
    {
      "year": 2023,
      "total_payments": 147365.97,
      "total_services": 2103,
      "total_beneficiaries": 1761,
      "avg_submitted": 198.21,
      "avg_paid": 78.56
    }
  ],
  "top_procedures": [
    {
      "code": "99291",
      "description": "Critical care delivery critically ill or injured patient, first 30-74 minutes",
      "services": 4718,
      "payments": 807645.46,
      "avg_markup": 2.2
    },
    {
      "code": "99214",
      "description": "Established patient office or other outpatient, visit typically 25 minutes",
      "services": 5995,
      "payments": 470430.33,
      "avg_markup": 1.77
    },
    {
      "code": "95811",
      "description": "Sleep monitoring of patient (6 years or older) in sleep lab with continued pressured respiratory assistance by mask or breathing tube",
      "services": 1534,
      "payments": 422200.84,
      "avg_markup": 4.19
    },
    {
      "code": "99233",
      "description": "Subsequent hospital inpatient care, typically 35 minutes per day",
      "services": 4005,
      "payments": 320136.45,
      "avg_markup": 1.88
    },
    {
      "code": "95810",
      "description": "Sleep monitoring of patient (6 years or older) in sleep lab",
      "services": 842,
      "payments": 214406.05,
      "avg_markup": 3.95
    },
    {
      "code": "99213",
      "description": "Established patient office or other outpatient visit, typically 15 minutes",
      "services": 2604,
      "payments": 142688.45,
      "avg_markup": 1.86
    },
    {
      "code": "32555",
      "description": "Removal of fluid from chest cavity with imaging guidance",
      "services": 481,
      "payments": 92023.8,
      "avg_markup": 3.86
    },
    {
      "code": "99204",
      "description": "New patient office or other outpatient visit, typically 45 minutes",
      "services": 766,
      "payments": 88680.41,
      "avg_markup": 1.73
    },
    {
      "code": "99232",
      "description": "Subsequent hospital inpatient care, typically 25 minutes per day",
      "services": 1291,
      "payments": 71222.16,
      "avg_markup": 2.35
    },
    {
      "code": "94060",
      "description": "Measurement and graphic recording of the amount and speed of breathed air, before and following medication administration",
      "services": 1379,
      "payments": 55305.35,
      "avg_markup": 3.24
    },
    {
      "code": "99222",
      "description": "Initial hospital inpatient care, typically 50 minutes per day",
      "services": 475,
      "payments": 48870.68,
      "avg_markup": 2.14
    },
    {
      "code": "76604",
      "description": "Ultrasound of chest",
      "services": 704,
      "payments": 39108.76,
      "avg_markup": 3.39
    },
    {
      "code": "94729",
      "description": "Measurement of lung diffusing capacity",
      "services": 818,
      "payments": 33329.77,
      "avg_markup": 2.45
    },
    {
      "code": "94726",
      "description": "Determination of lung volumes using plethysmography",
      "services": 796,
      "payments": 31415.5,
      "avg_markup": 2.53
    },
    {
      "code": "94660",
      "description": "Initiation and management of continued pressured respiratory assistance by mask or breathing tube",
      "services": 635,
      "payments": 28347.81,
      "avg_markup": 2.24
    },
    {
      "code": "99215",
      "description": "Established patient office or other outpatient, visit typically 40 minutes",
      "services": 254,
      "payments": 27316.84,
      "avg_markup": 1.67
    },
    {
      "code": "99292",
      "description": "Critical care delivery critically ill or injured patient",
      "services": 251,
      "payments": 21652.19,
      "avg_markup": 2.12
    },
    {
      "code": "G0008",
      "description": "Administration of influenza virus vaccine",
      "services": 947,
      "payments": 21316.23,
      "avg_markup": 1.55
    },
    {
      "code": "99239",
      "description": "Hospital discharge day management, more than 30 minutes",
      "services": 203,
      "payments": 16608.38,
      "avg_markup": 1.59
    },
    {
      "code": "90732",
      "description": "Vaccine for pneumococcal polysaccharide for injection beneath the skin or into muscle, patient 2 years or older",
      "services": 199,
      "payments": 16568.81,
      "avg_markup": 1.2
    }
  ],
  "overall": {
    "years_active": 10,
    "total_payments": 3137366.59,
    "total_services": 41872,
    "total_beneficiaries": 32420,
    "avg_markup_ratio": 2.61
  }
}