{
  "name": "Naz Wahab",
  "credentials": "MD",
  "specialty": "Family Practice",
  "city": "Las Vegas",
  "state": "NV",
  "entity_type": "Individual",
  "yearly_payments": [
    {
      "year": 2014,
      "total_payments": 374260.89,
      "total_services": 4290,
      "total_beneficiaries": 1591,
      "avg_submitted": 263.0,
      "avg_paid": 73.24
    },
    {
      "year": 2015,
      "total_payments": 402505.34,
      "total_services": 4953,
      "total_beneficiaries": 1908,
      "avg_submitted": 285.71,
      "avg_paid": 73.6
    },
    {
      "year": 2016,
      "total_payments": 370160.96,
      "total_services": 4767,
      "total_beneficiaries": 1924,
      "avg_submitted": 274.71,
      "avg_paid": 70.48
    },
    {
      "year": 2017,
      "total_payments": 140504.95,
      "total_services": 1634,
      "total_beneficiaries": 676,
      "avg_submitted": 270.04,
      "avg_paid": 79.1
    },
    {
      "year": 2018,
      "total_payments": 114425.69,
      "total_services": 1501,
      "total_beneficiaries": 708,
      "avg_submitted": 302.07,
      "avg_paid": 82.15
    },
    {
      "year": 2019,
      "total_payments": 412404.29,
      "total_services": 5402,
      "total_beneficiaries": 1712,
      "avg_submitted": 265.44,
      "avg_paid": 69.69
    },
    {
      "year": 2020,
      "total_payments": 802870.28,
      "total_services": 10065,
      "total_beneficiaries": 2412,
      "avg_submitted": 308.02,
      "avg_paid": 95.38
    },
    {
      "year": 2021,
      "total_payments": 280041.4,
      "total_services": 3491,
      "total_beneficiaries": 1167,
      "avg_submitted": 356.67,
      "avg_paid": 84.12
    },
    {
      "year": 2022,
      "total_payments": 199025.12,
      "total_services": 2404,
      "total_beneficiaries": 941,
      "avg_submitted": 322.46,
      "avg_paid": 80.17
    },
    {
      "year": 2023,
      "total_payments": 48421.59,
      "total_services": 705,
      "total_beneficiaries": 298,
      "avg_submitted": 192.25,
      "avg_paid": 77.55
    }
  ],
  "top_procedures": [
    {
      "code": "99233",
      "description": "Subsequent hospital inpatient care, typically 35 minutes per day",
      "services": 10377,
      "payments": 857436.67,
      "avg_markup": 3.23
    },
    {
      "code": "99309",
      "description": "Subsequent nursing facility visit, typically 25 minutes per day",
      "services": 7173,
      "payments": 512203.58,
      "avg_markup": 2.94
    },
    {
      "code": "99223",
      "description": "Initial hospital inpatient care, typically 70 minutes per day",
      "services": 2752,
      "payments": 438696.81,
      "avg_markup": 2.55
    },
    {
      "code": "11042",
      "description": "Removal of skin and tissue first 20 sq cm or less",
      "services": 6338,
      "payments": 342122.03,
      "avg_markup": 4.61
    },
    {
      "code": "99214",
      "description": "Established patient office or other outpatient, visit typically 25 minutes",
      "services": 4600,
      "payments": 327075.07,
      "avg_markup": 3.56
    },
    {
      "code": "99306",
      "description": "Initial nursing facility visit, typically 45 minutes per day",
      "services": 1675,
      "payments": 216778.98,
      "avg_markup": 2.77
    },
    {
      "code": "99310",
      "description": "Subsequent nursing facility visit, typically 35 minutes per day",
      "services": 1113,
      "payments": 116358.92,
      "avg_markup": 2.41
    },
    {
      "code": "99183",
      "description": "Management and supervision of oxygen chamber therapy per session",
      "services": 1025,
      "payments": 89794.38,
      "avg_markup": 6.03
    },
    {
      "code": "99204",
      "description": "New patient office or other outpatient visit, typically 45 minutes",
      "services": 703,
      "payments": 72436.56,
      "avg_markup": 3.93
    },
    {
      "code": "99232",
      "description": "Subsequent hospital inpatient care, typically 25 minutes per day",
      "services": 569,
      "payments": 32476.06,
      "avg_markup": 4.36
    },
    {
      "code": "11045",
      "description": "Removal of skin and tissue",
      "services": 1283,
      "payments": 29348.65,
      "avg_markup": 5.5
    },
    {
      "code": "15271",
      "description": "Application of skin substitute (wound surface up to 100 sq cm) to trunk, arms, or legs (first 25 sq cm or less)",
      "services": 295,
      "payments": 27398.93,
      "avg_markup": 5.38
    },
    {
      "code": "Q4158",
      "description": "Kerecis omega3, per square centimeter",
      "services": 56,
      "payments": 22542.32,
      "avg_markup": 1.25
    },
    {
      "code": "G0180",
      "description": "Physician certification for medicare-covered home health  services under a home health plan of care (patient not present), including contacts with home health agency and review of reports of patient status required by physicians to affirm the initial imple",
      "services": 389,
      "payments": 16350.01,
      "avg_markup": 3.22
    },
    {
      "code": "97597",
      "description": "Removal of tissue from wounds per session",
      "services": 388,
      "payments": 12503.85,
      "avg_markup": 7.46
    },
    {
      "code": "99213",
      "description": "Established patient office or other outpatient visit, typically 15 minutes",
      "services": 195,
      "payments": 10159.26,
      "avg_markup": 3.55
    },
    {
      "code": "99348",
      "description": "Established patient home visit, typically 25 minutes",
      "services": 78,
      "payments": 5112.98,
      "avg_markup": 4.22
    },
    {
      "code": "99222",
      "description": "Initial hospital inpatient care, typically 50 minutes per day",
      "services": 36,
      "payments": 3884.4,
      "avg_markup": 2.78
    },
    {
      "code": "15275",
      "description": "Application of skin substitute (wound surface up to 100 sq cm) to face, scalp, eyelids, mouth, neck, ears, eye region, genitals, hands, feet, and/or multiple fingers or toes (first 25 sq cm or less)",
      "services": 29,
      "payments": 3878.14,
      "avg_markup": 3.74
    },
    {
      "code": "99203",
      "description": "New patient office or other outpatient visit, typically 30 minutes",
      "services": 44,
      "payments": 2480.85,
      "avg_markup": 3.55
    }
  ],
  "overall": {
    "years_active": 10,
    "total_payments": 3144620.51,
    "total_services": 39212,
    "total_beneficiaries": 13337,
    "avg_markup_ratio": 3.37
  }
}