{
  "name": "Michael Levine",
  "credentials": "M.D.",
  "specialty": "Ophthalmology",
  "city": "Boynton Beach",
  "state": "FL",
  "entity_type": "Individual",
  "yearly_payments": [
    {
      "year": 2014,
      "total_payments": 1026008.99,
      "total_services": 8491,
      "total_beneficiaries": 7077,
      "avg_submitted": 566.38,
      "avg_paid": 180.49
    },
    {
      "year": 2015,
      "total_payments": 978958.86,
      "total_services": 8540,
      "total_beneficiaries": 7224,
      "avg_submitted": 744.17,
      "avg_paid": 181.84
    },
    {
      "year": 2016,
      "total_payments": 937532.8,
      "total_services": 8481,
      "total_beneficiaries": 7304,
      "avg_submitted": 568.24,
      "avg_paid": 141.76
    },
    {
      "year": 2017,
      "total_payments": 774836.75,
      "total_services": 6628,
      "total_beneficiaries": 5780,
      "avg_submitted": 772.5,
      "avg_paid": 174.81
    },
    {
      "year": 2018,
      "total_payments": 763820.66,
      "total_services": 6680,
      "total_beneficiaries": 5754,
      "avg_submitted": 730.0,
      "avg_paid": 158.56
    },
    {
      "year": 2019,
      "total_payments": 832024.29,
      "total_services": 7634,
      "total_beneficiaries": 6724,
      "avg_submitted": 571.55,
      "avg_paid": 134.83
    },
    {
      "year": 2020,
      "total_payments": 611438.77,
      "total_services": 5751,
      "total_beneficiaries": 5151,
      "avg_submitted": 569.73,
      "avg_paid": 123.82
    },
    {
      "year": 2021,
      "total_payments": 637362.11,
      "total_services": 5337,
      "total_beneficiaries": 4562,
      "avg_submitted": 562.32,
      "avg_paid": 125.94
    },
    {
      "year": 2022,
      "total_payments": 580273.64,
      "total_services": 5859,
      "total_beneficiaries": 5014,
      "avg_submitted": 358.45,
      "avg_paid": 80.54
    },
    {
      "year": 2023,
      "total_payments": 523537.46,
      "total_services": 5391,
      "total_beneficiaries": 4586,
      "avg_submitted": 423.48,
      "avg_paid": 92.68
    }
  ],
  "top_procedures": [
    {
      "code": "66984",
      "description": "Removal of cataract with insertion of lens",
      "services": 6161,
      "payments": 2963736.06,
      "avg_markup": 6.18
    },
    {
      "code": "92014",
      "description": "Eye and medical examination for diagnosis and treatment, established patient, 1 or more visits",
      "services": 18326,
      "payments": 1628191.67,
      "avg_markup": 1.81
    },
    {
      "code": "92012",
      "description": "Eye and medical examination for diagnosis and treatment, established patient",
      "services": 10879,
      "payments": 699719.51,
      "avg_markup": 1.94
    },
    {
      "code": "92004",
      "description": "Eye and medical examination for diagnosis and treatment, new patient, 1 or more visits",
      "services": 6029,
      "payments": 625008.77,
      "avg_markup": 2.08
    },
    {
      "code": "66821",
      "description": "Removal of recurring cataract in lens capsule using laser",
      "services": 2046,
      "payments": 533341.02,
      "avg_markup": 2.3
    },
    {
      "code": "92136",
      "description": "Measurement of corneal curvature and depth of eye",
      "services": 6780,
      "payments": 299357.69,
      "avg_markup": 4.53
    },
    {
      "code": "92134",
      "description": "Diagnostic imaging of retina",
      "services": 6022,
      "payments": 191041.14,
      "avg_markup": 3.15
    },
    {
      "code": "92083",
      "description": "Measurement of field of vision during daylight conditions",
      "services": 3498,
      "payments": 169123.68,
      "avg_markup": 2.58
    },
    {
      "code": "92250",
      "description": "Photography of the retina",
      "services": 3608,
      "payments": 154990.85,
      "avg_markup": 2.91
    },
    {
      "code": "66982",
      "description": "Removal of cataract with insertion of lens",
      "services": 125,
      "payments": 77542.88,
      "avg_markup": 4.84
    },
    {
      "code": "92133",
      "description": "Diagnostic imaging of optic nerve of eye",
      "services": 2635,
      "payments": 75895.72,
      "avg_markup": 3.47
    },
    {
      "code": "99204",
      "description": "New patient office or other outpatient visit, typically 45 minutes",
      "services": 489,
      "payments": 59277.49,
      "avg_markup": 1.65
    },
    {
      "code": "65855",
      "description": "Laser repair to improve eye fluid flow, 1 or more sessions",
      "services": 204,
      "payments": 44141.16,
      "avg_markup": 5.78
    },
    {
      "code": "68761",
      "description": "Closure of tear duct opening using plug",
      "services": 326,
      "payments": 37778.2,
      "avg_markup": 2.16
    },
    {
      "code": "0191T",
      "description": "Internal insertion of eye fluid drainage device",
      "services": 52,
      "payments": 30630.46,
      "avg_markup": 5.09
    },
    {
      "code": "66180",
      "description": "Creation of shunt to improve eye fluid flow",
      "services": 29,
      "payments": 27739.64,
      "avg_markup": 3.4
    },
    {
      "code": "92020",
      "description": "Examination of cornea and iris using lens device and slit lamp",
      "services": 833,
      "payments": 17352.31,
      "avg_markup": 3.6
    },
    {
      "code": "67255",
      "description": "Repair of defect of sclera with graft",
      "services": 19,
      "payments": 7995.29,
      "avg_markup": 2.85
    },
    {
      "code": "92002",
      "description": "Eye and medical examination for diagnosis and treatment, new patient",
      "services": 123,
      "payments": 6120.76,
      "avg_markup": 3.89
    },
    {
      "code": "67820",
      "description": "Removal of eyelashes by forceps",
      "services": 163,
      "payments": 4876.31,
      "avg_markup": 5.0
    }
  ],
  "overall": {
    "years_active": 10,
    "total_payments": 7665794.32,
    "total_services": 68792,
    "total_beneficiaries": 59176,
    "avg_markup_ratio": 3.85
  }
}