{
  "name": "Francis Metz",
  "credentials": "M.D.",
  "specialty": "Internal Medicine",
  "city": "Morgan City",
  "state": "LA",
  "entity_type": "Individual",
  "yearly_payments": [
    {
      "year": 2014,
      "total_payments": 278950.92,
      "total_services": 6699,
      "total_beneficiaries": 3672,
      "avg_submitted": 103.92,
      "avg_paid": 48.83
    },
    {
      "year": 2015,
      "total_payments": 336412.62,
      "total_services": 7030,
      "total_beneficiaries": 4348,
      "avg_submitted": 117.6,
      "avg_paid": 56.01
    },
    {
      "year": 2016,
      "total_payments": 314840.27,
      "total_services": 7260,
      "total_beneficiaries": 4272,
      "avg_submitted": 122.58,
      "avg_paid": 56.31
    },
    {
      "year": 2017,
      "total_payments": 338465.02,
      "total_services": 7641,
      "total_beneficiaries": 4391,
      "avg_submitted": 123.55,
      "avg_paid": 59.22
    },
    {
      "year": 2018,
      "total_payments": 333053.36,
      "total_services": 7817,
      "total_beneficiaries": 4329,
      "avg_submitted": 116.21,
      "avg_paid": 53.95
    },
    {
      "year": 2019,
      "total_payments": 297625.47,
      "total_services": 6722,
      "total_beneficiaries": 3684,
      "avg_submitted": 115.2,
      "avg_paid": 57.3
    },
    {
      "year": 2020,
      "total_payments": 225928.92,
      "total_services": 5280,
      "total_beneficiaries": 2974,
      "avg_submitted": 103.46,
      "avg_paid": 48.0
    },
    {
      "year": 2021,
      "total_payments": 228706.74,
      "total_services": 4920,
      "total_beneficiaries": 3168,
      "avg_submitted": 108.92,
      "avg_paid": 52.71
    },
    {
      "year": 2022,
      "total_payments": 187777.5,
      "total_services": 3527,
      "total_beneficiaries": 2111,
      "avg_submitted": 141.27,
      "avg_paid": 67.93
    },
    {
      "year": 2023,
      "total_payments": 213858.53,
      "total_services": 3933,
      "total_beneficiaries": 2324,
      "avg_submitted": 135.37,
      "avg_paid": 59.96
    }
  ],
  "top_procedures": [
    {
      "code": "99214",
      "description": "Established patient office or other outpatient, visit typically 25 minutes",
      "services": 6673,
      "payments": 463957.72,
      "avg_markup": 1.96
    },
    {
      "code": "99213",
      "description": "Established patient office or other outpatient visit, typically 15 minutes",
      "services": 8625,
      "payments": 397531.39,
      "avg_markup": 2.08
    },
    {
      "code": "G0439",
      "description": "Annual wellness visit, includes a personalized prevention plan of service (pps), subsequent visit",
      "services": 2714,
      "payments": 300537.54,
      "avg_markup": 2.41
    },
    {
      "code": "99231",
      "description": "Subsequent hospital inpatient care, typically 15 minutes per day",
      "services": 6557,
      "payments": 198219.12,
      "avg_markup": 2.96
    },
    {
      "code": "99223",
      "description": "Initial hospital inpatient care, typically 70 minutes per day",
      "services": 1157,
      "payments": 171347.43,
      "avg_markup": 2.25
    },
    {
      "code": "99232",
      "description": "Subsequent hospital inpatient care, typically 25 minutes per day",
      "services": 3108,
      "payments": 170730.09,
      "avg_markup": 1.95
    },
    {
      "code": "99239",
      "description": "Hospital discharge day management, more than 30 minutes",
      "services": 1489,
      "payments": 120253.37,
      "avg_markup": 2.59
    },
    {
      "code": "90662",
      "description": "Vaccine for influenza for injection into muscle",
      "services": 2085,
      "payments": 90267.05,
      "avg_markup": 1.11
    },
    {
      "code": "99222",
      "description": "Initial hospital inpatient care, typically 50 minutes per day",
      "services": 862,
      "payments": 85819.65,
      "avg_markup": 1.8
    },
    {
      "code": "99308",
      "description": "Subsequent nursing facility visit, typically 15 minutes per day",
      "services": 1669,
      "payments": 78935.67,
      "avg_markup": 1.89
    },
    {
      "code": "90670",
      "description": "Pneumococcal vaccine for injection into muscle",
      "services": 451,
      "payments": 73851.4,
      "avg_markup": 1.04
    },
    {
      "code": "G0008",
      "description": "Administration of influenza virus vaccine",
      "services": 2614,
      "payments": 51635.58,
      "avg_markup": 1.82
    },
    {
      "code": "83036",
      "description": "Hemoglobin A1C level",
      "services": 4095,
      "payments": 46330.78,
      "avg_markup": 4.2
    },
    {
      "code": "99233",
      "description": "Subsequent hospital inpatient care, typically 35 minutes per day",
      "services": 573,
      "payments": 45110.02,
      "avg_markup": 1.89
    },
    {
      "code": "G0438",
      "description": "Annual wellness visit; includes a personalized prevention plan of service (pps), initial visit",
      "services": 254,
      "payments": 40193.38,
      "avg_markup": 1.67
    },
    {
      "code": "G0181",
      "description": "Physician supervision of a patient receiving medicare-covered services provided by a participating home health agency (patient not present) requiring complex and multidisciplinary care modalities involving regular physician development and/or revision of c",
      "services": 475,
      "payments": 34523.69,
      "avg_markup": 2.43
    },
    {
      "code": "99490",
      "description": "Chronic care management services at least 20 minutes per calendar month",
      "services": 1087,
      "payments": 31831.91,
      "avg_markup": 2.22
    },
    {
      "code": "G0180",
      "description": "Physician certification for medicare-covered home health  services under a home health plan of care (patient not present), including contacts with home health agency and review of reports of patient status required by physicians to affirm the initial imple",
      "services": 763,
      "payments": 28170.32,
      "avg_markup": 2.58
    },
    {
      "code": "G0179",
      "description": "Physician re-certification for medicare-covered home health  services under a home health plan of care (patient not present), including contacts with home health agency and review of reports of patient status required by physicians to affirm the initial im",
      "services": 1011,
      "payments": 27757.65,
      "avg_markup": 2.6
    },
    {
      "code": "99238",
      "description": "Hospital discharge day management, 30 minutes or less",
      "services": 471,
      "payments": 25622.82,
      "avg_markup": 2.62
    }
  ],
  "overall": {
    "years_active": 10,
    "total_payments": 2755619.33,
    "total_services": 60829,
    "total_beneficiaries": 35273,
    "avg_markup_ratio": 2.2
  }
}