{
  "name": "Lifecare Ambulance",
  "credentials": "",
  "specialty": "Ambulance Service Provider",
  "city": "Battle Creek",
  "state": "MI",
  "entity_type": "Organization",
  "yearly_payments": [
    {
      "year": 2014,
      "total_payments": 2427246.77,
      "total_services": 16088,
      "total_beneficiaries": 9703,
      "avg_submitted": 698.37,
      "avg_paid": 277.09
    },
    {
      "year": 2015,
      "total_payments": 2281663.28,
      "total_services": 14944,
      "total_beneficiaries": 9266,
      "avg_submitted": 700.16,
      "avg_paid": 280.57
    },
    {
      "year": 2016,
      "total_payments": 2224999.06,
      "total_services": 14678,
      "total_beneficiaries": 8906,
      "avg_submitted": 698.23,
      "avg_paid": 279.27
    },
    {
      "year": 2017,
      "total_payments": 2103837.38,
      "total_services": 13829,
      "total_beneficiaries": 8566,
      "avg_submitted": 692.72,
      "avg_paid": 280.29
    },
    {
      "year": 2018,
      "total_payments": 2232763.62,
      "total_services": 14637,
      "total_beneficiaries": 9462,
      "avg_submitted": 693.33,
      "avg_paid": 283.47
    },
    {
      "year": 2019,
      "total_payments": 2549712.15,
      "total_services": 15975,
      "total_beneficiaries": 10174,
      "avg_submitted": 707.68,
      "avg_paid": 290.88
    },
    {
      "year": 2020,
      "total_payments": 1971115.51,
      "total_services": 12064,
      "total_beneficiaries": 8144,
      "avg_submitted": 749.89,
      "avg_paid": 296.2
    },
    {
      "year": 2021,
      "total_payments": 1797410.81,
      "total_services": 11063,
      "total_beneficiaries": 7477,
      "avg_submitted": 773.69,
      "avg_paid": 297.43
    },
    {
      "year": 2022,
      "total_payments": 1513112.02,
      "total_services": 9092,
      "total_beneficiaries": 6216,
      "avg_submitted": 824.01,
      "avg_paid": 307.04
    },
    {
      "year": 2023,
      "total_payments": 1671890.48,
      "total_services": 9319,
      "total_beneficiaries": 6198,
      "avg_submitted": 858.84,
      "avg_paid": 333.08
    }
  ],
  "top_procedures": [
    {
      "code": "A0427",
      "description": "Ambulance service, advanced life support, emergency transport, level 1 (als1-emergency)",
      "services": 41407,
      "payments": 13536154.97,
      "avg_markup": 2.71
    },
    {
      "code": "A0429",
      "description": "Ambulance service, basic life support, emergency transport (bls-emergency)",
      "services": 13998,
      "payments": 3906792.07,
      "avg_markup": 3.07
    },
    {
      "code": "A0428",
      "description": "Ambulance service, basic life support, non-emergency transport, (bls)",
      "services": 6670,
      "payments": 1152391.43,
      "avg_markup": 3.3
    },
    {
      "code": "A0434",
      "description": "Specialty care transport (sct)",
      "services": 1187,
      "payments": 680299.98,
      "avg_markup": 1.87
    },
    {
      "code": "A0426",
      "description": "Ambulance service, advanced life support, non-emergency transport, level 1 (als 1)",
      "services": 3243,
      "payments": 668721.81,
      "avg_markup": 3.61
    },
    {
      "code": "A0425",
      "description": "Ground mileage, per statute mile",
      "services": 64321,
      "payments": 421294.09,
      "avg_markup": 2.18
    },
    {
      "code": "A0433",
      "description": "Advanced life support, level 2 (als 2)",
      "services": 863,
      "payments": 408096.73,
      "avg_markup": 2.06
    }
  ],
  "overall": {
    "years_active": 10,
    "total_payments": 20773751.08,
    "total_services": 131689,
    "total_beneficiaries": 84112,
    "avg_markup_ratio": 2.79
  }
}