{
  "name": "Adedapo Oduwole",
  "credentials": "MD",
  "specialty": "Psychiatry",
  "city": "Myrtle Beach",
  "state": "SC",
  "entity_type": "Individual",
  "yearly_payments": [
    {
      "year": 2014,
      "total_payments": 517700.78,
      "total_services": 8653,
      "total_beneficiaries": 2674,
      "avg_submitted": 124.48,
      "avg_paid": 63.1
    },
    {
      "year": 2015,
      "total_payments": 503497.26,
      "total_services": 8113,
      "total_beneficiaries": 2625,
      "avg_submitted": 128.87,
      "avg_paid": 62.55
    },
    {
      "year": 2016,
      "total_payments": 531162.55,
      "total_services": 8537,
      "total_beneficiaries": 2582,
      "avg_submitted": 129.77,
      "avg_paid": 65.78
    },
    {
      "year": 2017,
      "total_payments": 751738.03,
      "total_services": 12096,
      "total_beneficiaries": 3733,
      "avg_submitted": 141.11,
      "avg_paid": 72.48
    },
    {
      "year": 2018,
      "total_payments": 618724.42,
      "total_services": 10336,
      "total_beneficiaries": 3061,
      "avg_submitted": 130.49,
      "avg_paid": 62.94
    },
    {
      "year": 2019,
      "total_payments": 595661.73,
      "total_services": 9388,
      "total_beneficiaries": 3066,
      "avg_submitted": 132.34,
      "avg_paid": 69.07
    },
    {
      "year": 2020,
      "total_payments": 525697.11,
      "total_services": 8094,
      "total_beneficiaries": 2639,
      "avg_submitted": 122.33,
      "avg_paid": 66.45
    },
    {
      "year": 2021,
      "total_payments": 418416.85,
      "total_services": 5862,
      "total_beneficiaries": 2013,
      "avg_submitted": 131.0,
      "avg_paid": 76.61
    },
    {
      "year": 2022,
      "total_payments": 303253.04,
      "total_services": 4142,
      "total_beneficiaries": 1464,
      "avg_submitted": 140.71,
      "avg_paid": 77.96
    },
    {
      "year": 2023,
      "total_payments": 298025.42,
      "total_services": 3958,
      "total_beneficiaries": 1298,
      "avg_submitted": 134.99,
      "avg_paid": 81.08
    }
  ],
  "top_procedures": [
    {
      "code": "99232",
      "description": "Subsequent hospital inpatient care, typically 25 minutes per day",
      "services": 24229,
      "payments": 1316906.44,
      "avg_markup": 1.58
    },
    {
      "code": "90837",
      "description": "Psychotherapy, 60 minutes with patient and/or family member",
      "services": 9690,
      "payments": 969819.72,
      "avg_markup": 1.75
    },
    {
      "code": "99214",
      "description": "Established patient office or other outpatient, visit typically 25 minutes",
      "services": 7321,
      "payments": 543632.77,
      "avg_markup": 1.75
    },
    {
      "code": "99222",
      "description": "Initial hospital inpatient care, typically 50 minutes per day",
      "services": 5017,
      "payments": 495890.01,
      "avg_markup": 1.67
    },
    {
      "code": "99231",
      "description": "Subsequent hospital inpatient care, typically 15 minutes per day",
      "services": 9426,
      "payments": 276974.53,
      "avg_markup": 2.56
    },
    {
      "code": "90833",
      "description": "Psychotherapy, 30 minutes with patient and/or family member",
      "services": 5881,
      "payments": 275962.22,
      "avg_markup": 1.56
    },
    {
      "code": "90836",
      "description": "Psychotherapy, 45 minutes with patient and/or family member",
      "services": 4065,
      "payments": 244404.71,
      "avg_markup": 1.66
    },
    {
      "code": "99239",
      "description": "Hospital discharge day management, more than 30 minutes",
      "services": 2860,
      "payments": 228155.43,
      "avg_markup": 2.07
    },
    {
      "code": "90792",
      "description": "Psychiatric diagnostic evaluation with medical services",
      "services": 1585,
      "payments": 172080.33,
      "avg_markup": 1.84
    },
    {
      "code": "99233",
      "description": "Subsequent hospital inpatient care, typically 35 minutes per day",
      "services": 2186,
      "payments": 170694.81,
      "avg_markup": 1.92
    },
    {
      "code": "99213",
      "description": "Established patient office or other outpatient visit, typically 15 minutes",
      "services": 2831,
      "payments": 156055.49,
      "avg_markup": 2.27
    },
    {
      "code": "99305",
      "description": "Initial nursing facility visit, typically 35 minutes per day",
      "services": 729,
      "payments": 68959.99,
      "avg_markup": 1.85
    },
    {
      "code": "99309",
      "description": "Subsequent nursing facility visit, typically 25 minutes per day",
      "services": 914,
      "payments": 56062.66,
      "avg_markup": 2.44
    },
    {
      "code": "90853",
      "description": "Group psychotherapy",
      "services": 1285,
      "payments": 24101.93,
      "avg_markup": 2.13
    },
    {
      "code": "90847",
      "description": "Family psychotherapy including patient",
      "services": 177,
      "payments": 13119.2,
      "avg_markup": 2.43
    },
    {
      "code": "99204",
      "description": "New patient office or other outpatient visit, typically 45 minutes",
      "services": 93,
      "payments": 10583.49,
      "avg_markup": 1.76
    },
    {
      "code": "99335",
      "description": "Established patient assisted living visit, typically 25 minutes",
      "services": 121,
      "payments": 7869.14,
      "avg_markup": 2.15
    },
    {
      "code": "99336",
      "description": "Established patient assisted living visit, typically 40 minutes",
      "services": 57,
      "payments": 5573.43,
      "avg_markup": 2.05
    },
    {
      "code": "90791",
      "description": "Psychiatric diagnostic evaluation",
      "services": 53,
      "payments": 4933.04,
      "avg_markup": 1.88
    },
    {
      "code": "99308",
      "description": "Subsequent nursing facility visit, typically 15 minutes per day",
      "services": 99,
      "payments": 4250.67,
      "avg_markup": 2.33
    }
  ],
  "overall": {
    "years_active": 10,
    "total_payments": 5063877.19,
    "total_services": 79179,
    "total_beneficiaries": 25155,
    "avg_markup_ratio": 1.78
  }
}